gravbody/__init__.py
gravbody/barnes_hut.py
gravbody/main.py
gravbody/nbody.py
gravbody/nbody_view.py
gravbody/physics_helper.py
gravbody/testing.py
gravbody-0.1.0.dist-info/LICENSE
gravbody-0.1.0.dist-info/METADATA
gravbody-0.1.0.dist-info/WHEEL
gravbody-0.1.0.dist-info/entry_points.txt
gravbody-0.1.0.dist-info/top_level.txt
gravbody-0.1.0.dist-info/RECORD
