Metadata-Version: 2.1
Name: gravbody
Version: 0.1.0
Summary: A gravitational n-body simulation package with features such as a barnes-hut tree, visualization tools, and CLI.
Home-page: https://codeberg.org/uzairn/nbody
Author: Uzair Nawaz
Author-email: uzairn@icloud.com
Classifier: Programming Language :: Python :: 3
Classifier: License :: OSI Approved :: GNU General Public License v3 or later (GPLv3+)
Classifier: Operating System :: OS Independent
Requires-Python: >=3.6
License-File: LICENSE
Requires-Dist: numpy
Requires-Dist: matplotlib
